lumicks/pylake/__about__.py
lumicks/pylake/__init__.py
lumicks/pylake/adjustments.py
lumicks/pylake/benchmark.py
lumicks/pylake/calibration.py
lumicks/pylake/channel.py
lumicks/pylake/conftest.py
lumicks/pylake/fdcurve.py
lumicks/pylake/fdensemble.py
lumicks/pylake/file.py
lumicks/pylake/file_download.py
lumicks/pylake/group.py
lumicks/pylake/image_stack.py
lumicks/pylake/kymo.py
lumicks/pylake/marker.py
lumicks/pylake/note.py
lumicks/pylake/point_scan.py
lumicks/pylake/scalebar.py
lumicks/pylake/scan.py
lumicks/pylake/detail/__init__.py
lumicks/pylake/detail/alignment.py
lumicks/pylake/detail/bead_cropping.py
lumicks/pylake/detail/confocal.py
lumicks/pylake/detail/h5_helper.py
lumicks/pylake/detail/image.py
lumicks/pylake/detail/imaging_mixins.py
lumicks/pylake/detail/mixin.py
lumicks/pylake/detail/plotting.py
lumicks/pylake/detail/timeindex.py
lumicks/pylake/detail/utilities.py
lumicks/pylake/detail/value.py
lumicks/pylake/detail/widefield.py
lumicks/pylake/detail/tests/test_bead_crop.py
lumicks/pylake/detail/tests/test_plotting.py
lumicks/pylake/detail/tests/test_value.py
lumicks/pylake/detail/tests/test_widefield.py
lumicks/pylake/detail/tests/data/kymo_sum0.npz
lumicks/pylake/detail/tests/data/kymo_sum1.npz
lumicks/pylake/detail/tests/data/kymo_sum2.npz
lumicks/pylake/detail/tests/data/kymo_sum3.npz
lumicks/pylake/detail/tests/data/kymo_sum4.npz
lumicks/pylake/detail/tests/data/kymo_sum5.npz
lumicks/pylake/detail/tests/data/kymo_sum6.npz
lumicks/pylake/detail/tests/data/kymo_sum7.npz
lumicks/pylake/fitting/__init__.py
lumicks/pylake/fitting/datasets.py
lumicks/pylake/fitting/fit.py
lumicks/pylake/fitting/fitdata.py
lumicks/pylake/fitting/model.py
lumicks/pylake/fitting/models.py
lumicks/pylake/fitting/parameter_trace.py
lumicks/pylake/fitting/parameters.py
lumicks/pylake/fitting/profile_likelihood.py
lumicks/pylake/fitting/detail/__init__.py
lumicks/pylake/fitting/detail/derivative_manipulation.py
lumicks/pylake/fitting/detail/link_functions.py
lumicks_pylake-1.7.0.dist-info/METADATA
lumicks_pylake-1.7.0.dist-info/WHEEL
lumicks_pylake-1.7.0.dist-info/top_level.txt
lumicks_pylake-1.7.0.dist-info/RECORD
