Metadata-Version: 2.4
Name: lumicks.pylake
Version: 1.7.0
Summary: Bluelake data analysis tools
Author: Lumicks B.V.
Author-email: pylake@lumicks.com
License: Copyright (c) 2025, LUMICKS B.V.
Project-URL: Homepage, https://github.com/lumicks/pylake
Project-URL: Documentation, https://lumicks-pylake.readthedocs.io/en/stable/
Project-URL: Source, https://github.com/lumicks/pylake
Keywords: optical tweezers,kymographs,data analysis,lumicks
Classifier: Development Status :: 5 - Production/Stable
Classifier: Intended Audience :: Science/Research
Classifier: Topic :: Scientific/Engineering :: Physics
Classifier: Operating System :: OS Independent
Classifier: Programming Language :: Python :: 3 :: Only
Classifier: Programming Language :: Python :: 3.10
Classifier: Programming Language :: Python :: 3.11
Classifier: Programming Language :: Python :: 3.12
Classifier: Programming Language :: Python :: Implementation :: CPython
Requires-Python: >=3.10
Requires-Dist: pytest>=7.4
Requires-Dist: h5py<4,>=3.4
Requires-Dist: numpy>=1.24
Requires-Dist: scipy<2,>=1.9
Requires-Dist: matplotlib>=3.8
Requires-Dist: tifffile>=2022.7.28
Requires-Dist: tabulate<0.9,>=0.8.8
Requires-Dist: cachetools>=3.1
Requires-Dist: deprecated>=1.2.8
Requires-Dist: scikit-learn>=0.18.0
Requires-Dist: scikit-image>=0.17.2
Requires-Dist: tqdm>=4.27.0
Provides-Extra: notebook
Requires-Dist: notebook>=7; extra == "notebook"
Requires-Dist: ipywidgets>=7.0.0; extra == "notebook"
Requires-Dist: jupyter_client>=8; extra == "notebook"
Requires-Dist: ipympl>=0.9.3; extra == "notebook"
